sila2lib/__init__.py
sila2lib/sila_client.py
sila2lib/sila_server.py
sila2lib/sila_service_detection.py
sila2lib/_internal/__init__.py
sila2lib/_internal/config.py
sila2lib/animl/__init__.py
sila2lib/error_handling/__init__.py
sila2lib/error_handling/client_err.py
sila2lib/error_handling/server_err.py
sila2lib/error_handling/tests/__init__.py
sila2lib/error_handling/tests/test_client_get_error_details.py
sila2lib/error_handling/tests/test_client_grpc_error_handling.py
sila2lib/error_handling/tests/test_server_execution_err.py
sila2lib/error_handling/tests/test_server_framework_err.py
sila2lib/error_handling/tests/test_server_validation_err.py
sila2lib/fdl_parser/__init__.py
sila2lib/fdl_parser/command.py
sila2lib/fdl_parser/constraint_content_type.py
sila2lib/fdl_parser/constraint_schema.py
sila2lib/fdl_parser/constraint_unit.py
sila2lib/fdl_parser/data_type_definition.py
sila2lib/fdl_parser/data_type_intermediate.py
sila2lib/fdl_parser/data_type_parameter.py
sila2lib/fdl_parser/data_type_response.py
sila2lib/fdl_parser/fdl_parser.py
sila2lib/fdl_parser/fdl_sila_reader.py
sila2lib/fdl_parser/fdl_validator.py
sila2lib/fdl_parser/metadata.py
sila2lib/fdl_parser/property.py
sila2lib/fdl_parser/standard_errors.py
sila2lib/fdl_parser/type_base.py
sila2lib/fdl_parser/type_basic.py
sila2lib/fdl_parser/type_constrained.py
sila2lib/fdl_parser/type_data_type_identifier.py
sila2lib/fdl_parser/type_list.py
sila2lib/fdl_parser/type_structured.py
sila2lib/fdl_parser/exceptions/__init__.py
sila2lib/fdl_parser/exceptions/exceptions.py
sila2lib/fdl_parser/tests/__init__.py
sila2lib/fdl_parser/tests/_data_command.py
sila2lib/fdl_parser/tests/_data_data_type_definition.py
sila2lib/fdl_parser/tests/_data_data_type_parameter.py
sila2lib/fdl_parser/tests/_data_metadata.py
sila2lib/fdl_parser/tests/_data_property.py
sila2lib/fdl_parser/tests/_data_standard_errors.py
sila2lib/fdl_parser/tests/_data_type_basic.py
sila2lib/fdl_parser/tests/_data_type_constrained.py
sila2lib-0.2.5.dist-info/LICENSE
sila2lib-0.2.5.dist-info/METADATA
sila2lib-0.2.5.dist-info/WHEEL
sila2lib-0.2.5.dist-info/top_level.txt
sila2lib-0.2.5.dist-info/RECORD
