Metadata-Version: 2.1
Name: sila2lib
Version: 0.2.5
Summary: sila2lib - a SiLA 2 python3 library 
Home-page: https://gitlab.com/SiLA2/sila_python
Author: Mark Doerr, Timm Severin, Lukas Bromig, Florian Meinicke, Robert Giessmann, Maximilian Schulz (max@unitelabs.ch)
Author-email: mark.doerr@uni-greifswald.de
License: MIT
Keywords: SiLA 2,lab automation,laboratory,instruments,experiments,evaluation,visualisation,serial interface,robots
Platform: UNKNOWN
Classifier: License :: OSI Approved :: MIT License
Classifier: Intended Audience :: Developers
Classifier: Operating System :: OS Independent
Classifier: Programming Language :: Python
Classifier: Programming Language :: Python :: 3.7
Classifier: Programming Language :: Python :: 3.8
Classifier: Topic :: Utilities
Classifier: Topic :: Scientific/Engineering
Classifier: Topic :: Scientific/Engineering :: Interface Engine/Protocol Translator
Classifier: Topic :: Scientific/Engineering :: Information Analysis
Requires-Dist: wheel
Requires-Dist: grpcio (>=1.7)
Requires-Dist: grpcio-tools
Requires-Dist: lxml
Requires-Dist: zeroconf
